liquidrocketpy/__init__.py
liquidrocketpy/rl.py
liquidrocketpy-0.1.5.dist-info/METADATA
liquidrocketpy-0.1.5.dist-info/WHEEL
liquidrocketpy-0.1.5.dist-info/licenses/LICENSE
liquidrocketpy-0.1.5.dist-info/RECORD
