Metadata-Version: 2.1
Name: liquidrocketpy
Version: 0.1.5
Summary: A package for data from the rl liquipedia pages
Project-URL: Homepage, https://github.com/nmcassa/liquidrocketpy
Project-URL: Bug Tracker, https://github.com/nmcassa/liquidrocketpy/issues
Author-email: Nicholas Cassarino <nmcassa804@outlook.com>
License-File: LICENSE
Classifier: License :: OSI Approved :: MIT License
Classifier: Operating System :: OS Independent
Classifier: Programming Language :: Python :: 3
Requires-Python: >=3.7
